pyvinorm/__init__.py
pyvinorm/cli.py
pyvinorm/vinorm.py
pyvinorm/managers/__init__.py
pyvinorm/managers/mapping.py
pyvinorm/managers/vocab.py
pyvinorm/patterns/__init__.py
pyvinorm/patterns/base.py
pyvinorm/patterns/handler.py
pyvinorm/patterns/registry.py
pyvinorm/patterns/patterns/__init__.py
pyvinorm/patterns/patterns/address.py
pyvinorm/patterns/patterns/datetime.py
pyvinorm/patterns/patterns/math.py
pyvinorm/patterns/patterns/special.py
pyvinorm/resources/mapping/Acronyms.txt
pyvinorm/resources/mapping/Acronyms_shorten.txt
pyvinorm/resources/mapping/BaseUnit.txt
pyvinorm/resources/mapping/CurrencyUnit.txt
pyvinorm/resources/mapping/Domain.txt
pyvinorm/resources/mapping/LetterSoundEN.txt
pyvinorm/resources/mapping/LetterSoundVN.txt
pyvinorm/resources/mapping/Number.txt
pyvinorm/resources/mapping/PrefixUnit.txt
pyvinorm/resources/mapping/Symbol.txt
pyvinorm/resources/mapping/Teencode.txt
pyvinorm/resources/vocabulary/Popular.txt
pyvinorm/utils/__init__.py
pyvinorm/utils/number_converter.py
pyvinorm/utils/string_utils.py
pyvinorm-0.1.0.dist-info/METADATA
pyvinorm-0.1.0.dist-info/WHEEL
pyvinorm-0.1.0.dist-info/entry_points.txt
pyvinorm-0.1.0.dist-info/RECORD
